eobot/__init__.py
eobot/_version.py
eobot/lib/__init__.py
eobot/lib/eobot_authentication.py
eobot/lib/eobot_config.py
eobot/lib/eobot_errors.py
eobot/lib/eobot_request.py
eobot/methods/__init__.py
eobot/methods/exchange_coins.py
eobot/methods/get_balances.py
eobot/methods/get_coin_value.py
eobot/methods/get_deposit_address.py
eobot/methods/get_exchange_estimate.py
eobot/methods/get_exchange_rate.py
eobot/methods/get_mining_estimates.py
eobot/methods/get_mining_mode.py
eobot/methods/get_mining_speed.py
eobot/methods/get_supported_coins.py
eobot/methods/get_supported_fiat.py
eobot/methods/get_user_id.py
eobot/methods/manual_withdraw.py
eobot/methods/set_automatic_withdraw.py
eobot/methods/set_mining_mode.py
eobot_py-0.1.2.dist-info/DESCRIPTION.rst
eobot_py-0.1.2.dist-info/METADATA
eobot_py-0.1.2.dist-info/RECORD
eobot_py-0.1.2.dist-info/WHEEL
eobot_py-0.1.2.dist-info/metadata.json
eobot_py-0.1.2.dist-info/top_level.txt
