Metadata-Version: 2.0
Name: eobot-py
Version: 0.1.2
Summary: Eobot API wrapper
Home-page: http://github.com/rickdenhaan/eobot-py
Author: Rick den Haan
Author-email: rick@capirussa.nl
License: Freeware
Keywords: eobot eobot.com api
Platform: UNKNOWN
Classifier: Development Status :: 4 - Beta
Classifier: Intended Audience :: Developers
Classifier: License :: Freeware
Classifier: Programming Language :: Python :: 2.7
Classifier: Programming Language :: Python :: 3.3
Classifier: Programming Language :: Python :: 3.4
Classifier: Programming Language :: Python :: 3.5
Classifier: Programming Language :: Python :: 3.6
Classifier: Topic :: Utilities
Classifier: Topic :: Internet :: WWW/HTTP
Classifier: Topic :: Software Development :: Libraries
Requires-Dist: requests
